bshot/__init__.py
bshot/exceptions.py
bshot/py.typed
bshot/screenshot.py
bshot-1.0.5.dist-info/licenses/LICENSE
bshot-1.0.5.dist-info/METADATA
bshot-1.0.5.dist-info/WHEEL
bshot-1.0.5.dist-info/top_level.txt
bshot-1.0.5.dist-info/RECORD
