Metadata-Version: 2.4
Name: bshot
Version: 1.0.5
Summary: Python package to take screenshots of windows that are in background
Home-page: https://github.com/sandbox-pokhara/bshot
Author: Pradish Bijukchhe
Author-email: Pradish Bijukchhe <pradish@sandbox.com.np>
License: Copyright (c) 2025 Pradish Bijukchhe
Project-URL: Homepage, https://github.com/sandbox-pokhara/bshot
Project-URL: Issues, https://github.com/sandbox-pokhara/bshot/issues
Classifier: Programming Language :: Python :: 3
Requires-Python: >=3
License-File: LICENSE
Requires-Dist: numpy
Requires-Dist: pywin32; sys_platform == "win32"
Dynamic: author
Dynamic: home-page
Dynamic: license-file
Dynamic: requires-python
